alignak_checks_glpi/__init__.py
alignak_checks_glpi-1.1.0.data/data/share/alignak/etc/arbiter/packs/glpi/commands.cfg
alignak_checks_glpi-1.1.0.data/data/share/alignak/etc/arbiter/packs/glpi/groups.cfg
alignak_checks_glpi-1.1.0.data/data/share/alignak/etc/arbiter/packs/glpi/templates.cfg
alignak_checks_glpi-1.1.0.data/data/share/alignak/etc/backend-json/glpi/commands.json
alignak_checks_glpi-1.1.0.data/data/share/alignak/etc/backend-json/glpi/hostgroups.json
alignak_checks_glpi-1.1.0.data/data/share/alignak/etc/backend-json/glpi/hosts-templates.json
alignak_checks_glpi-1.1.0.data/data/share/alignak/etc/backend-json/glpi/servicegroups.json
alignak_checks_glpi-1.1.0.data/data/share/alignak/etc/backend-json/glpi/services-templates.json
alignak_checks_glpi-1.1.0.data/data/share/alignak/etc/backend-json/glpi/setup.sh
alignak_checks_glpi-1.1.0.dist-info/LICENSE
alignak_checks_glpi-1.1.0.dist-info/METADATA
alignak_checks_glpi-1.1.0.dist-info/WHEEL
alignak_checks_glpi-1.1.0.dist-info/top_level.txt
alignak_checks_glpi-1.1.0.dist-info/RECORD
